{
    "mp_id": "mp-18002",
    "nelements": 4,
    "nsites": 36,
    "elements": [
        "Ge",
        "K",
        "Li",
        "O"
    ],
    "structure": {
        "@module": "pymatgen.core.structure",
        "@class": "Structure",
        "charge": null,
        "lattice": {
            "matrix": [
                [
                    5.87484669,
                    -0.0006011,
                    -0.00080622
                ],
                [
                    1.35000792,
                    7.37717693,
                    -0.000378
                ],
                [
                    2.32981373,
                    0.7356712,
                    9.66059683
                ]
            ],
            "a": 5.874846776071344,
            "b": 7.4996840589101454,
            "c": 9.964756657481004,
            "alpha": 83.41601581242678,
            "beta": 76.48707078404158,
            "gamma": 79.63559906020555,
            "volume": 418.7107046524872
        },
        "sites": [
            {
                "species": [
                    {
                        "element": "K",
                        "occu": 1
                    }
                ],
                "abc": [
                    0.49864545,
                    0.11719248,
                    0.61625228
                ],
                "xyz": [
                    4.523429370668307,
                    1.3176089783758274,
                    5.9529185059561325
                ],
                "label": "K",
                "properties": {}
            },
            {
                "species": [
                    {
                        "element": "K",
                        "occu": 1
                    }
                ],
                "abc": [
                    0.50135455,
                    0.88280752,
                    0.38374772
                ],
                "xyz": [
                    5.031238969331694,
                    6.7946380516241724,
                    3.7064941040438666
                ],
                "label": "K",
                "properties": {}
            },
            {
                "species": [
                    {
                        "element": "K",
                        "occu": 1
                    }
                ],
                "abc": [
                    0.46092527,
                    0.35983929,
                    0.87243324
                ],
                "xyz": [
                    5.226258129284419,
                    3.2961450551064706,
                    8.42771816630783
                ],
                "label": "K",
                "properties": {}
            },
            {
                "species": [
                    {
                        "element": "K",
                        "occu": 1
                    }
                ],
                "abc": [
                    0.53907473,
                    0.64016071,
                    0.12756676
                ],
                "xyz": [
                    4.328410210715582,
                    4.816101974893529,
                    1.2316944436921702
                ],
                "label": "K",
                "properties": {}
            },
            {
                "species": [
                    {
                        "element": "Li",
                        "occu": 1
                    }
                ],
                "abc": [
                    0.97503647,
                    0.82131805,
                    0.11401108
                ],
                "xyz": [
                    7.102600230303869,
                    6.142297144267365,
                    1.100318525907133
                ],
                "label": "Li",
                "properties": {}
            },
            {
                "species": [
                    {
                        "element": "Li",
                        "occu": 1
                    }
                ],
                "abc": [
                    0.02496353,
                    0.17868195,
                    0.88598892
                ],
                "xyz": [
                    2.452068109696131,
                    1.9699498857326345,
                    8.559094084092866
                ],
                "label": "Li",
                "properties": {}
            },
            {
                "species": [
                    {
                        "element": "Li",
                        "occu": 1
                    }
                ],
                "abc": [
                    0.3050299,
                    0.32323405,
                    0.35356985
                ],
                "xyz": [
                    3.0521243169237473,
                    2.644482579010897,
                    3.4153276684166975
                ],
                "label": "Li",
                "properties": {}
            },
            {
                "species": [
                    {
                        "element": "Li",
                        "occu": 1
                    }
                ],
                "abc": [
                    0.6949701,
                    0.67676595,
                    0.64643015
                ],
                "xyz": [
                    6.502544023076253,
                    5.467764450989103,
                    6.244084941583302
                ],
                "label": "Li",
                "properties": {}
            },
            {
                "species": [
                    {
                        "element": "Li",
                        "occu": 1
                    }
                ],
                "abc": [
                    0.9309655,
                    0.54854654,
                    0.87587093
                ],
                "xyz": [
                    8.250437878089661,
                    4.690518294675488,
                    8.460478016249622
                ],
                "label": "Li",
                "properties": {}
            },
            {
                "species": [
                    {
                        "element": "Li",
                        "occu": 1
                    }
                ],
                "abc": [
                    0.0690345,
                    0.45145346,
                    0.12412907
                ],
                "xyz": [
                    1.3042304619103393,
                    3.421728735324512,
                    1.1989345937503781
                ],
                "label": "Li",
                "properties": {}
            },
            {
                "species": [
                    {
                        "element": "Li",
                        "occu": 1
                    }
                ],
                "abc": [
                    0.03613996,
                    0.92654602,
                    0.62833935
                ],
                "xyz": [
                    2.9270748343564863,
                    7.297523363219082,
                    6.069753761620148
                ],
                "label": "Li",
                "properties": {}
            },
            {
                "species": [
                    {
                        "element": "Li",
                        "occu": 1
                    }
                ],
                "abc": [
                    0.31019986,
                    0.05157383,
                    0.10317791
                ],
                "xyz": [
                    2.1323870110749015,
                    0.45618782459508794,
                    0.996490606033156
                ],
                "label": "Li",
                "properties": {}
            },
            {
                "species": [
                    {
                        "element": "Li",
                        "occu": 1
                    }
                ],
                "abc": [
                    0.68983279,
                    0.44349015,
                    0.39561752
                ],
                "xyz": [
                    5.573092227851502,
                    3.562335060451595,
                    3.8211775633358074
                ],
                "label": "Li",
                "properties": {}
            },
            {
                "species": [
                    {
                        "element": "Li",
                        "occu": 1
                    }
                ],
                "abc": [
                    0.31016721,
                    0.55650985,
                    0.60438248
                ],
                "xyz": [
                    3.9815761121484976,
                    4.549911969548405,
                    5.838235046664193
                ],
                "label": "Li",
                "properties": {}
            },
            {
                "species": [
                    {
                        "element": "Li",
                        "occu": 1
                    }
                ],
                "abc": [
                    0.96386004,
                    0.07345398,
                    0.37166065
                ],
                "xyz": [
                    6.627593505643515,
                    0.8147236667809175,
                    3.5896588483798504
                ],
                "label": "Li",
                "properties": {}
            },
            {
                "species": [
                    {
                        "element": "Li",
                        "occu": 1
                    }
                ],
                "abc": [
                    0.68980014,
                    0.94842617,
                    0.89682209
                ],
                "xyz": [
                    7.422281328925099,
                    7.656059205404913,
                    8.662922003966843
                ],
                "label": "Li",
                "properties": {}
            },
            {
                "species": [
                    {
                        "element": "Ge",
                        "occu": 1
                    }
                ],
                "abc": [
                    0.94377891,
                    0.29184362,
                    0.63357838
                ],
                "xyz": [
                    7.414667212661936,
                    2.618520082237542,
                    6.119874079063355
                ],
                "label": "Ge",
                "properties": {}
            },
            {
                "species": [
                    {
                        "element": "Ge",
                        "occu": 1
                    }
                ],
                "abc": [
                    0.05622109,
                    0.70815638,
                    0.36642162
                ],
                "xyz": [
                    2.1400011273380644,
                    5.493726947762459,
                    3.5395385309366447
                ],
                "label": "Ge",
                "properties": {}
            },
            {
                "species": [
                    {
                        "element": "Ge",
                        "occu": 1
                    }
                ],
                "abc": [
                    0.33324324,
                    0.794752,
                    0.85157479
                ],
                "xyz": [
                    5.014685077778583,
                    6.489304854608845,
                    8.226151633160963
                ],
                "label": "Ge",
                "properties": {}
            },
            {
                "species": [
                    {
                        "element": "Ge",
                        "occu": 1
                    }
                ],
                "abc": [
                    0.66675676,
                    0.205248,
                    0.14842521
                ],
                "xyz": [
                    4.539983262221417,
                    1.6229421753911561,
                    1.433260976839037
                ],
                "label": "Ge",
                "properties": {}
            },
            {
                "species": [
                    {
                        "element": "O",
                        "occu": 1
                    }
                ],
                "abc": [
                    0.6784176,
                    0.21111362,
                    0.32637728
                ],
                "xyz": [
                    5.031002718921668,
                    1.7971210954837624,
                    3.15237256176619
                ],
                "label": "O",
                "properties": {}
            },
            {
                "species": [
                    {
                        "element": "O",
                        "occu": 1
                    }
                ],
                "abc": [
                    0.3215824,
                    0.78888638,
                    0.67362272
                ],
                "xyz": [
                    4.523665621078331,
                    6.315125934516237,
                    6.507040048233809
                ],
                "label": "O",
                "properties": {}
            },
            {
                "species": [
                    {
                        "element": "O",
                        "occu": 1
                    }
                ],
                "abc": [
                    0.8657557,
                    0.33847752,
                    0.03320725
                ],
                "xyz": [
                    5.620496048221134,
                    2.5209177635725433,
                    0.31997592002000347
                ],
                "label": "O",
                "properties": {}
            },
            {
                "species": [
                    {
                        "element": "O",
                        "occu": 1
                    }
                ],
                "abc": [
                    0.1342443,
                    0.66152248,
                    0.96679275
                ],
                "xyz": [
                    3.934172291778866,
                    5.591329266427457,
                    9.339436689979996
                ],
                "label": "O",
                "properties": {}
            },
            {
                "species": [
                    {
                        "element": "O",
                        "occu": 1
                    }
                ],
                "abc": [
                    0.64217774,
                    0.70436418,
                    0.84848536
                ],
                "xyz": [
                    6.700405833226979,
                    5.820039408948485,
                    8.196090992919826
                ],
                "label": "O",
                "properties": {}
            },
            {
                "species": [
                    {
                        "element": "O",
                        "occu": 1
                    }
                ],
                "abc": [
                    0.35782226,
                    0.29563582,
                    0.15151464
                ],
                "xyz": [
                    2.854262506773021,
                    2.2922076210515145,
                    1.463321617080174
                ],
                "label": "O",
                "properties": {}
            },
            {
                "species": [
                    {
                        "element": "O",
                        "occu": 1
                    }
                ],
                "abc": [
                    0.68825997,
                    0.43777319,
                    0.59206756
                ],
                "xyz": [
                    6.013826210653264,
                    3.6646836171188117,
                    5.719005626063002
                ],
                "label": "O",
                "properties": {}
            },
            {
                "species": [
                    {
                        "element": "O",
                        "occu": 1
                    }
                ],
                "abc": [
                    0.31174003,
                    0.56222681,
                    0.40793244
                ],
                "xyz": [
                    3.540842129346737,
                    4.4475634128811885,
                    3.9404069839369984
                ],
                "label": "O",
                "properties": {}
            },
            {
                "species": [
                    {
                        "element": "O",
                        "occu": 1
                    }
                ],
                "abc": [
                    0.15050315,
                    0.89166922,
                    0.24195803
                ],
                "xyz": [
                    2.651660582010048,
                    6.755912685811365,
                    2.337000587996292
                ],
                "label": "O",
                "properties": {}
            },
            {
                "species": [
                    {
                        "element": "O",
                        "occu": 1
                    }
                ],
                "abc": [
                    0.84949685,
                    0.10833078,
                    0.75804197
                ],
                "xyz": [
                    6.903007757989952,
                    1.3563343441886344,
                    7.322412022003707
                ],
                "label": "O",
                "properties": {}
            },
            {
                "species": [
                    {
                        "element": "O",
                        "occu": 1
                    }
                ],
                "abc": [
                    0.87940944,
                    0.82825298,
                    0.51052102
                ],
                "xyz": [
                    7.4739626023519605,
                    6.485215774653991,
                    4.930915670355209
                ],
                "label": "O",
                "properties": {}
            },
            {
                "species": [
                    {
                        "element": "O",
                        "occu": 1
                    }
                ],
                "abc": [
                    0.12059056,
                    0.17174702,
                    0.48947898
                ],
                "xyz": [
                    2.08070573764804,
                    1.6270312553460087,
                    4.72849693964479
                ],
                "label": "O",
                "properties": {}
            },
            {
                "species": [
                    {
                        "element": "O",
                        "occu": 1
                    }
                ],
                "abc": [
                    0.89131568,
                    0.6024477,
                    0.27669957
                ],
                "xyz": [
                    6.69431059604998,
                    4.647387408817697,
                    2.672136667046233
                ],
                "label": "O",
                "properties": {}
            },
            {
                "species": [
                    {
                        "element": "O",
                        "occu": 1
                    }
                ],
                "abc": [
                    0.10868432,
                    0.3975523,
                    0.72330043
                ],
                "xyz": [
                    2.860357743950021,
                    3.4648596211823026,
                    6.987275942953766
                ],
                "label": "O",
                "properties": {}
            },
            {
                "species": [
                    {
                        "element": "O",
                        "occu": 1
                    }
                ],
                "abc": [
                    0.69220843,
                    0.98318935,
                    0.08996645
                ],
                "xyz": [
                    5.603536883584607,
                    7.318931430385663,
                    0.8681998838216188
                ],
                "label": "O",
                "properties": {}
            },
            {
                "species": [
                    {
                        "element": "O",
                        "occu": 1
                    }
                ],
                "abc": [
                    0.30779157,
                    0.01681065,
                    0.91003355
                ],
                "xyz": [
                    3.9511314564153928,
                    0.7933155996143375,
                    8.79121272617838
                ],
                "label": "O",
                "properties": {}
            }
        ]
    },
    "spacegroup": {
        "source": "spglib",
        "symbol": "P-1",
        "number": 2,
        "point_group": "-1",
        "crystal_system": "triclinic",
        "hall": "-P 1"
    },
    "dielectric": {
        "epsilon_ionic": [
            [
                5.65475037,
                -0.30660759,
                -0.54084032
            ],
            [
                -0.30660759,
                5.15233909,
                -0.83123204
            ],
            [
                -0.54084032,
                -0.83123204,
                4.765029
            ]
        ],
        "epsilon_ionic_avg": 5.190706153333335,
        "epsilon_ionic_eig": [
            3.8907327080489793,
            5.93566657861368,
            5.745719173337344
        ],
        "epsilon_electronic": [
            [
                2.94899333,
                -0.01043618,
                -0.0125572
            ],
            [
                -0.010436,
                2.93114095,
                -0.0160193
            ],
            [
                -0.0125573,
                -0.01602007,
                2.93825682
            ]
        ],
        "epsilon_electronic_avg": 2.9394636999999997,
        "epsilon_electronic_eig": [
            2.9114267728738437,
            2.9572827075767534,
            2.949681619549401
        ]
    },
    "phonon": {
        "lowest_freq": -0.1269318422823332,
        "frequency": [
            -0.1269318422823332,
            -0.10438745353168602,
            -0.07396398427306974,
            2.622569384510389,
            2.764374145579078,
            3.0632323578934404,
            3.329966005381981,
            3.5165381050698197,
            3.5370214869605765,
            3.6555917716260247,
            3.8123176074503555,
            3.8222414980764174,
            4.022884682037888,
            4.15457210778293,
            4.236786138839967,
            4.52349231375304,
            4.776156109368404,
            4.83290091004008,
            4.839626305177593,
            4.935499034476415,
            5.012420807306674,
            5.309084964858389,
            5.364977031534928,
            5.387762866259852,
            5.889066938433083,
            5.925538757468129,
            5.961044164741839,
            6.014131116849418,
            6.258431114304531,
            6.41894263167375,
            6.440254722081202,
            6.596797654524206,
            6.685278788464449,
            6.931070273023095,
            6.984926006035812,
            7.047691735073082,
            7.151585700157599,
            7.254236430878738,
            7.593385554605961,
            7.7691533567126605,
            7.887096037191007,
            8.035182047880946,
            8.121999285156635,
            8.204435755774,
            8.273700978520816,
            8.61908926719329,
            8.823580540953294,
            8.95082122299692,
            9.068733043539966,
            9.429695095176372,
            9.48369960005289,
            9.611351348774445,
            9.825709534892097,
            9.843340966651185,
            10.063507032330113,
            10.13076872373304,
            10.292102904147626,
            10.58187904957447,
            10.894263710733657,
            10.928406956829303,
            10.981432825438246,
            11.393348537058213,
            11.613891451318695,
            11.76163570980435,
            11.906179616811047,
            12.04772469080356,
            12.14474215450941,
            12.50066594514443,
            12.873100308789258,
            13.167604213299763,
            13.407490989838331,
            13.532580189598926,
            13.657964186964799,
            13.691350224788406,
            13.789914157135401,
            13.947028818876106,
            14.458209952488374,
            14.463869681833309,
            14.700075320492928,
            14.757837824951189,
            14.927939353859896,
            15.00700847370011,
            15.122460135263262,
            15.204559073406072,
            15.323395021270912,
            15.374567175860019,
            15.510533713988586,
            15.524895187010253,
            15.736470533366893,
            15.98586351805072,
            16.214871234491515,
            16.224563480852453,
            20.229199147997818,
            20.240230101493673,
            20.295922204407887,
            20.637840649776344,
            20.719784222234313,
            20.73686502190553,
            20.93889938369368,
            21.273359709655786,
            21.33166091545865,
            21.727710919434358,
            21.745896221025983,
            21.891278404677,
            22.231700372489108,
            22.26405116402204,
            22.353875398894964,
            22.71192518238276
        ]
    },
    "born_effective_charge": {
        "avg_abs_trace": 1.5517750925925924,
        "tensors": [
            [
                [
                    1.26289,
                    -0.0141,
                    -0.00381
                ],
                [
                    -0.01295,
                    1.13043,
                    -0.05841
                ],
                [
                    -0.06488,
                    -0.0498,
                    1.14511
                ]
            ],
            [
                [
                    1.26293,
                    -0.01408,
                    -0.0038
                ],
                [
                    -0.01296,
                    1.13039,
                    -0.05845
                ],
                [
                    -0.06486,
                    -0.04978,
                    1.14511
                ]
            ],
            [
                [
                    1.14558,
                    -0.00641,
                    0.03009
                ],
                [
                    0.02881,
                    1.21633,
                    0.0245
                ],
                [
                    0.03496,
                    0.01717,
                    1.19483
                ]
            ],
            [
                [
                    1.14562,
                    -0.00641,
                    0.03004
                ],
                [
                    0.02884,
                    1.21633,
                    0.02449
                ],
                [
                    0.03494,
                    0.01717,
                    1.19482
                ]
            ],
            [
                [
                    0.87866,
                    -0.12551,
                    -0.00455
                ],
                [
                    -0.17235,
                    0.8827,
                    -0.05937
                ],
                [
                    -0.0265,
                    0.02005,
                    1.11787
                ]
            ],
            [
                [
                    0.87866,
                    -0.12551,
                    -0.00455
                ],
                [
                    -0.17235,
                    0.8827,
                    -0.05937
                ],
                [
                    -0.02649,
                    0.02005,
                    1.11787
                ]
            ],
            [
                [
                    0.86496,
                    -0.07871,
                    -0.19381
                ],
                [
                    -0.06329,
                    0.99949,
                    0.09203
                ],
                [
                    -0.20129,
                    -0.0136,
                    1.00988
                ]
            ],
            [
                [
                    0.86496,
                    -0.07871,
                    -0.19381
                ],
                [
                    -0.06329,
                    0.99949,
                    0.09203
                ],
                [
                    -0.20129,
                    -0.0136,
                    1.00988
                ]
            ],
            [
                [
                    1.12223,
                    0.06095,
                    0.08042
                ],
                [
                    -0.01428,
                    1.13782,
                    0.02754
                ],
                [
                    -0.06903,
                    -0.04224,
                    1.03975
                ]
            ],
            [
                [
                    1.12223,
                    0.06094,
                    0.08041
                ],
                [
                    -0.01428,
                    1.13782,
                    0.02754
                ],
                [
                    -0.06902,
                    -0.04224,
                    1.03975
                ]
            ],
            [
                [
                    0.93487,
                    -0.03435,
                    0.04395
                ],
                [
                    0.05026,
                    1.08882,
                    0.05099
                ],
                [
                    0.22528,
                    0.00344,
                    0.90803
                ]
            ],
            [
                [
                    1.0925,
                    0.1207,
                    0.02832
                ],
                [
                    0.21493,
                    0.94029,
                    0.03047
                ],
                [
                    -0.02556,
                    -0.05091,
                    1.06426
                ]
            ],
            [
                [
                    1.16909,
                    0.07067,
                    0.04614
                ],
                [
                    -0.02616,
                    1.02776,
                    -0.10072
                ],
                [
                    0.11768,
                    0.11817,
                    0.97176
                ]
            ],
            [
                [
                    1.16909,
                    0.07068,
                    0.04614
                ],
                [
                    -0.02617,
                    1.02775,
                    -0.10072
                ],
                [
                    0.11769,
                    0.11817,
                    0.97177
                ]
            ],
            [
                [
                    0.93486,
                    -0.03434,
                    0.04396
                ],
                [
                    0.05027,
                    1.08882,
                    0.051
                ],
                [
                    0.22528,
                    0.00344,
                    0.90803
                ]
            ],
            [
                [
                    1.0925,
                    0.12069,
                    0.02832
                ],
                [
                    0.21493,
                    0.94029,
                    0.03047
                ],
                [
                    -0.02557,
                    -0.05092,
                    1.06424
                ]
            ],
            [
                [
                    2.69385,
                    -0.06428,
                    -0.02262
                ],
                [
                    -0.03441,
                    2.78811,
                    -0.08214
                ],
                [
                    0.03916,
                    -0.02946,
                    2.80864
                ]
            ],
            [
                [
                    2.69392,
                    -0.06433,
                    -0.02256
                ],
                [
                    -0.03436,
                    2.78814,
                    -0.0821
                ],
                [
                    0.03911,
                    -0.02954,
                    2.80857
                ]
            ],
            [
                [
                    2.69665,
                    0.00817,
                    -0.06194
                ],
                [
                    -0.00916,
                    2.7405,
                    0.07681
                ],
                [
                    -0.02765,
                    0.0439,
                    2.82427
                ]
            ],
            [
                [
                    2.69668,
                    0.00823,
                    -0.06194
                ],
                [
                    -0.00916,
                    2.74044,
                    0.07688
                ],
                [
                    -0.02767,
                    0.04394,
                    2.82424
                ]
            ],
            [
                [
                    -1.54307,
                    0.01215,
                    -0.27359
                ],
                [
                    0.05853,
                    -1.5298,
                    -0.03796
                ],
                [
                    -0.2512,
                    -0.09462,
                    -2.14149
                ]
            ],
            [
                [
                    -1.54316,
                    0.01208,
                    -0.27401
                ],
                [
                    0.05871,
                    -1.52988,
                    -0.03727
                ],
                [
                    -0.25123,
                    -0.09463,
                    -2.14186
                ]
            ],
            [
                [
                    -1.75996,
                    -0.31317,
                    0.28798
                ],
                [
                    -0.23883,
                    -1.72062,
                    0.21365
                ],
                [
                    0.36723,
                    0.25617,
                    -1.84046
                ]
            ],
            [
                [
                    -1.75998,
                    -0.31313,
                    0.28811
                ],
                [
                    -0.23889,
                    -1.72072,
                    0.21371
                ],
                [
                    0.36745,
                    0.25626,
                    -1.8405
                ]
            ],
            [
                [
                    -2.09688,
                    0.29732,
                    0.00117
                ],
                [
                    0.32423,
                    -1.6467,
                    -0.07619
                ],
                [
                    -0.00881,
                    0.00646,
                    -1.50619
                ]
            ],
            [
                [
                    -2.09684,
                    0.29738,
                    0.00118
                ],
                [
                    0.32434,
                    -1.64675,
                    -0.07615
                ],
                [
                    -0.00896,
                    0.0065,
                    -1.50622
                ]
            ],
            [
                [
                    -1.97845,
                    0.36609,
                    -0.1107
                ],
                [
                    0.42469,
                    -1.77874,
                    0.16729
                ],
                [
                    -0.15136,
                    0.10257,
                    -1.50654
                ]
            ],
            [
                [
                    -1.97934,
                    0.36665,
                    -0.11081
                ],
                [
                    0.42495,
                    -1.77892,
                    0.16733
                ],
                [
                    -0.15152,
                    0.10271,
                    -1.50652
                ]
            ],
            [
                [
                    -1.54817,
                    -0.17429,
                    0.20722
                ],
                [
                    -0.16354,
                    -1.79737,
                    0.38566
                ],
                [
                    0.14312,
                    0.37937,
                    -1.87421
                ]
            ],
            [
                [
                    -1.54805,
                    -0.17397,
                    0.20695
                ],
                [
                    -0.16356,
                    -1.79735,
                    0.38578
                ],
                [
                    0.14319,
                    0.37958,
                    -1.87432
                ]
            ],
            [
                [
                    -1.51358,
                    0.16482,
                    0.24045
                ],
                [
                    0.04623,
                    -1.70893,
                    -0.27271
                ],
                [
                    0.17158,
                    -0.33029,
                    -1.95645
                ]
            ],
            [
                [
                    -1.5135,
                    0.16494,
                    0.24039
                ],
                [
                    0.04638,
                    -1.70884,
                    -0.27277
                ],
                [
                    0.1716,
                    -0.3302,
                    -1.95639
                ]
            ],
            [
                [
                    -1.91796,
                    -0.28822,
                    -0.24675
                ],
                [
                    -0.28163,
                    -1.65102,
                    -0.13633
                ],
                [
                    -0.22093,
                    -0.14219,
                    -1.65744
                ]
            ],
            [
                [
                    -1.91781,
                    -0.28827,
                    -0.24685
                ],
                [
                    -0.28095,
                    -1.65062,
                    -0.13592
                ],
                [
                    -0.22103,
                    -0.14234,
                    -1.65751
                ]
            ],
            [
                [
                    -1.50305,
                    -0.00279,
                    -0.0477
                ],
                [
                    -0.13175,
                    -2.11879,
                    -0.24576
                ],
                [
                    -0.05174,
                    -0.19455,
                    -1.60132
                ]
            ],
            [
                [
                    -1.50295,
                    -0.00189,
                    -0.04744
                ],
                [
                    -0.13177,
                    -2.11939,
                    -0.24585
                ],
                [
                    -0.05169,
                    -0.19423,
                    -1.60127
                ]
            ]
        ]
    },
    "band_gap": 3.8747000000000003,
    "is_direct": false,
    "formula": "KLi3GeO4"
}