{
    "mp_id": "mp-1195626",
    "nelements": 4,
    "nsites": 36,
    "elements": [
        "B",
        "Cd",
        "O",
        "Sr"
    ],
    "structure": {
        "@module": "pymatgen.core.structure",
        "@class": "Structure",
        "charge": null,
        "lattice": {
            "matrix": [
                [
                    3.81753179,
                    -5.07799579,
                    -0.00107084
                ],
                [
                    3.81753179,
                    5.07799579,
                    -0.00107084
                ],
                [
                    -1.82239862,
                    0.0,
                    10.99976031
                ]
            ],
            "a": 6.352919908012113,
            "b": 6.352919908012113,
            "c": 11.149702399958,
            "alpha": 95.6461162438531,
            "beta": 95.6461162438531,
            "gamma": 106.12982734880637,
            "volume": 426.4499155032927
        },
        "sites": [
            {
                "species": [
                    {
                        "element": "Sr",
                        "occu": 1
                    }
                ],
                "abc": [
                    0.63158987,
                    0.36841013,
                    0.75
                ],
                "xyz": [
                    2.450732825,
                    -1.3364256117332944,
                    8.248749392499999
                ],
                "label": "Sr",
                "properties": {}
            },
            {
                "species": [
                    {
                        "element": "Sr",
                        "occu": 1
                    }
                ],
                "abc": [
                    0.36841013,
                    0.63158987,
                    0.25
                ],
                "xyz": [
                    3.361932135,
                    1.3364256117332944,
                    2.7488692374999997
                ],
                "label": "Sr",
                "properties": {}
            },
            {
                "species": [
                    {
                        "element": "Sr",
                        "occu": 1
                    }
                ],
                "abc": [
                    0.8176366,
                    0.1823634,
                    0.25
                ],
                "xyz": [
                    3.361932135,
                    -3.2259146350998287,
                    2.7488692374999997
                ],
                "label": "Sr",
                "properties": {}
            },
            {
                "species": [
                    {
                        "element": "Sr",
                        "occu": 1
                    }
                ],
                "abc": [
                    0.1823634,
                    0.8176366,
                    0.75
                ],
                "xyz": [
                    2.450732825,
                    3.2259146350998287,
                    8.248749392499999
                ],
                "label": "Sr",
                "properties": {}
            },
            {
                "species": [
                    {
                        "element": "Cd",
                        "occu": 1
                    }
                ],
                "abc": [
                    0.73819413,
                    0.93505181,
                    0.55697884
                ],
                "xyz": [
                    5.372632099053233,
                    0.9996424702691677,
                    6.1248419590594505
                ],
                "label": "Cd",
                "properties": {}
            },
            {
                "species": [
                    {
                        "element": "Cd",
                        "occu": 1
                    }
                ],
                "abc": [
                    0.06494819,
                    0.26180587,
                    0.94302116
                ],
                "xyz": [
                    -0.4711664490532319,
                    0.9996424702691671,
                    10.372656825940549
                ],
                "label": "Cd",
                "properties": {}
            },
            {
                "species": [
                    {
                        "element": "Cd",
                        "occu": 1
                    }
                ],
                "abc": [
                    0.26180587,
                    0.06494819,
                    0.44302116
                ],
                "xyz": [
                    0.4400328609467682,
                    -0.9996424702691671,
                    4.8727766709405484
                ],
                "label": "Cd",
                "properties": {}
            },
            {
                "species": [
                    {
                        "element": "Cd",
                        "occu": 1
                    }
                ],
                "abc": [
                    0.93505181,
                    0.73819413,
                    0.05697884
                ],
                "xyz": [
                    6.283831409053232,
                    -0.9996424702691677,
                    0.6249618040594508
                ],
                "label": "Cd",
                "properties": {}
            },
            {
                "species": [
                    {
                        "element": "B",
                        "occu": 1
                    }
                ],
                "abc": [
                    0.72897705,
                    0.45660065,
                    0.50510562
                ],
                "xyz": [
                    3.605476774422838,
                    -1.3831262124953563,
                    5.554771187209674
                ],
                "label": "B",
                "properties": {}
            },
            {
                "species": [
                    {
                        "element": "B",
                        "occu": 1
                    }
                ],
                "abc": [
                    0.54339935,
                    0.27102295,
                    0.99489438
                ],
                "xyz": [
                    1.295988875577161,
                    -1.3831262124953556,
                    10.942727597790325
                ],
                "label": "B",
                "properties": {}
            },
            {
                "species": [
                    {
                        "element": "B",
                        "occu": 1
                    }
                ],
                "abc": [
                    0.27102295,
                    0.54339935,
                    0.49489438
                ],
                "xyz": [
                    2.207188185577161,
                    1.3831262124953556,
                    5.442847442790326
                ],
                "label": "B",
                "properties": {}
            },
            {
                "species": [
                    {
                        "element": "B",
                        "occu": 1
                    }
                ],
                "abc": [
                    0.45660065,
                    0.72897705,
                    0.00510562
                ],
                "xyz": [
                    4.516676084422838,
                    1.3831262124953563,
                    0.054891032209674194
                ],
                "label": "B",
                "properties": {}
            },
            {
                "species": [
                    {
                        "element": "B",
                        "occu": 1
                    }
                ],
                "abc": [
                    0.67416679,
                    0.86937961,
                    0.8314013
                ],
                "xyz": [
                    4.37739286955385,
                    0.9912898781140274,
                    9.143562130195425
                ],
                "label": "B",
                "properties": {}
            },
            {
                "species": [
                    {
                        "element": "B",
                        "occu": 1
                    }
                ],
                "abc": [
                    0.13062039,
                    0.32583321,
                    0.6685987
                ],
                "xyz": [
                    0.5240727804461498,
                    0.9912898781140277,
                    7.353936654804572
                ],
                "label": "B",
                "properties": {}
            },
            {
                "species": [
                    {
                        "element": "B",
                        "occu": 1
                    }
                ],
                "abc": [
                    0.32583321,
                    0.13062039,
                    0.1685987
                ],
                "xyz": [
                    1.4352720904461498,
                    -0.9912898781140277,
                    1.8540564998045728
                ],
                "label": "B",
                "properties": {}
            },
            {
                "species": [
                    {
                        "element": "B",
                        "occu": 1
                    }
                ],
                "abc": [
                    0.86937961,
                    0.67416679,
                    0.3314013
                ],
                "xyz": [
                    5.2885921795538495,
                    -0.9912898781140274,
                    3.6436819751954266
                ],
                "label": "B",
                "properties": {}
            },
            {
                "species": [
                    {
                        "element": "O",
                        "occu": 1
                    }
                ],
                "abc": [
                    0.81430109,
                    0.62352583,
                    0.59827609
                ],
                "xyz": [
                    4.398652454822789,
                    -0.9687559671161554,
                    6.579353906624974
                ],
                "label": "O",
                "properties": {}
            },
            {
                "species": [
                    {
                        "element": "O",
                        "occu": 1
                    }
                ],
                "abc": [
                    0.37647417,
                    0.18569891,
                    0.90172391
                ],
                "xyz": [
                    0.5028131951772092,
                    -0.9687559671161553,
                    9.918144878375024
                ],
                "label": "O",
                "properties": {}
            },
            {
                "species": [
                    {
                        "element": "O",
                        "occu": 1
                    }
                ],
                "abc": [
                    0.18569891,
                    0.37647417,
                    0.40172391
                ],
                "xyz": [
                    1.414012505177209,
                    0.9687559671161553,
                    4.4182647233750245
                ],
                "label": "O",
                "properties": {}
            },
            {
                "species": [
                    {
                        "element": "O",
                        "occu": 1
                    }
                ],
                "abc": [
                    0.62352583,
                    0.81430109,
                    0.09827609
                ],
                "xyz": [
                    5.30985176482279,
                    0.9687559671161554,
                    1.079473751624975
                ],
                "label": "O",
                "properties": {}
            },
            {
                "species": [
                    {
                        "element": "O",
                        "occu": 1
                    }
                ],
                "abc": [
                    0.61146063,
                    0.97120728,
                    0.73875385
                ],
                "xyz": [
                    4.695581062678171,
                    1.8267919741666043,
                    8.12442049398495
                ],
                "label": "O",
                "properties": {}
            },
            {
                "species": [
                    {
                        "element": "O",
                        "occu": 1
                    }
                ],
                "abc": [
                    0.02879272,
                    0.38853937,
                    0.76124615
                ],
                "xyz": [
                    0.20588458732182802,
                    1.8267919741666034,
                    8.37307829101505
                ],
                "label": "O",
                "properties": {}
            },
            {
                "species": [
                    {
                        "element": "O",
                        "occu": 1
                    }
                ],
                "abc": [
                    0.38853937,
                    0.02879272,
                    0.26124615
                ],
                "xyz": [
                    1.117083897321828,
                    -1.8267919741666034,
                    2.873198136015051
                ],
                "label": "O",
                "properties": {}
            },
            {
                "species": [
                    {
                        "element": "O",
                        "occu": 1
                    }
                ],
                "abc": [
                    0.97120728,
                    0.61146063,
                    0.23875385
                ],
                "xyz": [
                    5.606780372678171,
                    -1.8267919741666043,
                    2.6245403389849487
                ],
                "label": "O",
                "properties": {}
            },
            {
                "species": [
                    {
                        "element": "O",
                        "occu": 1
                    }
                ],
                "abc": [
                    0.63193266,
                    0.24313083,
                    0.52557128
                ],
                "xyz": [
                    2.3827823159597132,
                    -1.974334055884296,
                    5.780221052832265
                ],
                "label": "O",
                "properties": {}
            },
            {
                "species": [
                    {
                        "element": "O",
                        "occu": 1
                    }
                ],
                "abc": [
                    0.75686917,
                    0.36806734,
                    0.97442872
                ],
                "xyz": [
                    2.518683334040286,
                    -1.9743340558842954,
                    10.717277732167734
                ],
                "label": "O",
                "properties": {}
            },
            {
                "species": [
                    {
                        "element": "O",
                        "occu": 1
                    }
                ],
                "abc": [
                    0.36806734,
                    0.75686917,
                    0.47442872
                ],
                "xyz": [
                    3.429882644040286,
                    1.9743340558842954,
                    5.217397577167734
                ],
                "label": "O",
                "properties": {}
            },
            {
                "species": [
                    {
                        "element": "O",
                        "occu": 1
                    }
                ],
                "abc": [
                    0.24313083,
                    0.63193266,
                    0.02557128
                ],
                "xyz": [
                    3.2939816259597134,
                    1.974334055884296,
                    0.2803408978322652
                ],
                "label": "O",
                "properties": {}
            },
            {
                "species": [
                    {
                        "element": "O",
                        "occu": 1
                    }
                ],
                "abc": [
                    0.87335751,
                    0.88538759,
                    0.37325364
                ],
                "xyz": [
                    6.033848411310752,
                    0.06108869559336405,
                    4.103817240232144
                ],
                "label": "O",
                "properties": {}
            },
            {
                "species": [
                    {
                        "element": "O",
                        "occu": 1
                    }
                ],
                "abc": [
                    0.11461241,
                    0.12664249,
                    0.12674636
                ],
                "xyz": [
                    0.6900158586892478,
                    0.06108869559336316,
                    1.3939212347678553
                ],
                "label": "O",
                "properties": {}
            },
            {
                "species": [
                    {
                        "element": "O",
                        "occu": 1
                    }
                ],
                "abc": [
                    0.12664249,
                    0.11461241,
                    0.62674636
                ],
                "xyz": [
                    -0.221183451310752,
                    -0.06108869559336316,
                    6.893801389767854
                ],
                "label": "O",
                "properties": {}
            },
            {
                "species": [
                    {
                        "element": "O",
                        "occu": 1
                    }
                ],
                "abc": [
                    0.88538759,
                    0.87335751,
                    0.87325364
                ],
                "xyz": [
                    5.122649101310751,
                    -0.06108869559336405,
                    9.603697395232144
                ],
                "label": "O",
                "properties": {}
            },
            {
                "species": [
                    {
                        "element": "O",
                        "occu": 1
                    }
                ],
                "abc": [
                    0.73059063,
                    0.49431234,
                    0.38159762
                ],
                "xyz": [
                    3.9806830515571328,
                    -1.199820161888399,
                    4.196170679770067
                ],
                "label": "O",
                "properties": {}
            },
            {
                "species": [
                    {
                        "element": "O",
                        "occu": 1
                    }
                ],
                "abc": [
                    0.50568766,
                    0.26940937,
                    0.11840238
                ],
                "xyz": [
                    2.743181218442868,
                    -1.1998201618883992,
                    1.3015677952299325
                ],
                "label": "O",
                "properties": {}
            },
            {
                "species": [
                    {
                        "element": "O",
                        "occu": 1
                    }
                ],
                "abc": [
                    0.26940937,
                    0.50568766,
                    0.61840238
                ],
                "xyz": [
                    1.8319819084428681,
                    1.1998201618883992,
                    6.8014479502299325
                ],
                "label": "O",
                "properties": {}
            },
            {
                "species": [
                    {
                        "element": "O",
                        "occu": 1
                    }
                ],
                "abc": [
                    0.49431234,
                    0.73059063,
                    0.88159762
                ],
                "xyz": [
                    3.0694837415571326,
                    1.199820161888399,
                    9.696050834770068
                ],
                "label": "O",
                "properties": {}
            }
        ]
    },
    "spacegroup": {
        "source": "spglib",
        "symbol": "C2/c",
        "number": 15,
        "point_group": "2/m",
        "crystal_system": "monoclinic",
        "hall": "-C 2yc"
    },
    "dielectric": {
        "epsilon_ionic": [
            [
                7.81419532,
                -0.0,
                0.3402567
            ],
            [
                -0.0,
                4.54857999,
                -2e-08
            ],
            [
                0.3402567,
                -2e-08,
                5.55976574
            ]
        ],
        "epsilon_ionic_avg": 5.97418035,
        "epsilon_ionic_eig": [
            7.864430233677247,
            5.509530826322752,
            4.5485799899999995
        ],
        "epsilon_electronic": [
            [
                3.39865467,
                0.0,
                -0.08390424
            ],
            [
                0.0,
                3.28123256,
                0.0
            ],
            [
                -0.08390387,
                0.0,
                3.35912148
            ]
        ],
        "epsilon_electronic_avg": 3.3463362366666662,
        "epsilon_electronic_eig": [
            3.465089053667895,
            3.2926870963321053,
            3.28123256
        ]
    },
    "phonon": {
        "lowest_freq": -0.0841979697806545,
        "frequency": [
            -0.0841979697806545,
            -0.04628960931429358,
            -0.03614328015112496,
            1.8170038873219923,
            1.9877079297102604,
            2.169501435046865,
            2.1721334607742904,
            2.4103290723650685,
            2.727015659791694,
            2.8445366333176367,
            3.014229042169589,
            3.0214070160829634,
            3.1457812712808733,
            3.16221697546709,
            3.3713589430556636,
            3.4257272971969743,
            3.7205806115436735,
            3.7603003843599425,
            3.908403181105651,
            4.030055962215585,
            4.073639427523192,
            4.0939535287752715,
            4.225409032145361,
            4.440865437398669,
            4.52574088286157,
            4.692002099048601,
            4.774277172189273,
            5.285266315748994,
            5.412621706181131,
            5.483175567753055,
            5.5625976385992315,
            5.588172838263285,
            5.806664863370311,
            5.882487775193368,
            6.042581150825199,
            6.2639151126929296,
            6.277030517423806,
            6.382554524438352,
            6.416382255215701,
            6.614644205633677,
            6.679923461912126,
            6.807377631759703,
            6.812450882504645,
            7.055560713500706,
            7.459576346936432,
            7.5630386675704475,
            7.6072780504235125,
            7.69445196606946,
            8.245101323157389,
            8.414450960000048,
            8.45027717677631,
            8.822426046464471,
            8.866836203752294,
            9.070442345821201,
            9.144897072715265,
            9.316494836432533,
            9.963817017797496,
            10.261749304912795,
            10.397386652236253,
            10.47749593980091,
            13.029026142623689,
            13.096946064734837,
            13.12851368611669,
            13.375842557042239,
            14.39418182476642,
            14.407321159380514,
            14.423654580305186,
            14.778635499324253,
            17.164217122115975,
            17.235506867912516,
            17.586726773181365,
            17.682970873240883,
            18.45805727976875,
            18.534046730350347,
            18.56154389331113,
            18.693355462622158,
            20.00827996148793,
            20.01856114715968,
            20.630279120694414,
            20.73067921653301,
            21.201734317183785,
            21.204499148329262,
            21.522862076922788,
            21.541667330309473,
            23.43826758247243,
            23.578525659287568,
            23.65309954487418,
            23.772382242714578,
            28.863874372750303,
            28.904206937586192,
            28.949387989738078,
            28.98630009184268,
            33.22129710093894,
            33.250797109472714,
            33.761286825160894,
            34.16038046379606,
            36.407880344476034,
            36.54033843271871,
            37.07825032787023,
            37.122209174215165,
            38.696984262847984,
            38.71209421800981,
            39.23658107894259,
            39.3493051038007,
            40.090367474949524,
            40.21401586969353,
            40.600385565982215,
            41.43690251764712
        ]
    },
    "born_effective_charge": {
        "avg_abs_trace": 2.0233438888888893,
        "tensors": [
            [
                [
                    2.42304,
                    -2e-05,
                    -0.20164
                ],
                [
                    -0.0,
                    2.45777,
                    0.0
                ],
                [
                    -0.28629,
                    -4e-05,
                    2.69796
                ]
            ],
            [
                [
                    2.42304,
                    2e-05,
                    -0.20164
                ],
                [
                    -0.0,
                    2.45727,
                    0.0
                ],
                [
                    -0.28629,
                    4e-05,
                    2.69796
                ]
            ],
            [
                [
                    2.54365,
                    4e-05,
                    0.21126
                ],
                [
                    -0.0,
                    2.70369,
                    0.0
                ],
                [
                    0.2356,
                    4e-05,
                    2.41511
                ]
            ],
            [
                [
                    2.54365,
                    -4e-05,
                    0.21126
                ],
                [
                    -0.0,
                    2.70373,
                    0.0
                ],
                [
                    0.2356,
                    -4e-05,
                    2.41511
                ]
            ],
            [
                [
                    2.44355,
                    0.03127,
                    -0.01313
                ],
                [
                    0.04643,
                    2.49298,
                    0.04713
                ],
                [
                    0.00755,
                    0.13685,
                    2.34235
                ]
            ],
            [
                [
                    2.44353,
                    -0.03126,
                    -0.01312
                ],
                [
                    -0.04643,
                    2.49298,
                    -0.04713
                ],
                [
                    0.00752,
                    -0.13687,
                    2.34234
                ]
            ],
            [
                [
                    2.44353,
                    0.03126,
                    -0.01312
                ],
                [
                    0.04644,
                    2.49299,
                    0.04716
                ],
                [
                    0.00752,
                    0.13687,
                    2.34234
                ]
            ],
            [
                [
                    2.44355,
                    -0.03127,
                    -0.01313
                ],
                [
                    -0.04644,
                    2.49299,
                    -0.04716
                ],
                [
                    0.00755,
                    -0.13685,
                    2.34235
                ]
            ],
            [
                [
                    2.57109,
                    0.89255,
                    -0.29992
                ],
                [
                    1.05626,
                    1.00589,
                    0.05992
                ],
                [
                    -0.09223,
                    0.02823,
                    2.6798
                ]
            ],
            [
                [
                    2.57109,
                    -0.89255,
                    -0.29992
                ],
                [
                    -1.05626,
                    1.00589,
                    -0.05992
                ],
                [
                    -0.09224,
                    -0.02824,
                    2.67979
                ]
            ],
            [
                [
                    2.57109,
                    0.89255,
                    -0.29992
                ],
                [
                    1.05617,
                    1.00589,
                    0.05994
                ],
                [
                    -0.09224,
                    0.02824,
                    2.67979
                ]
            ],
            [
                [
                    2.57109,
                    -0.89255,
                    -0.29992
                ],
                [
                    -1.05617,
                    1.00589,
                    -0.05994
                ],
                [
                    -0.09223,
                    -0.02823,
                    2.6798
                ]
            ],
            [
                [
                    2.18193,
                    -0.57443,
                    -0.53009
                ],
                [
                    -0.61148,
                    2.00619,
                    -0.85453
                ],
                [
                    -0.58298,
                    -1.20857,
                    1.97083
                ]
            ],
            [
                [
                    2.18192,
                    0.57444,
                    -0.53008
                ],
                [
                    0.61148,
                    2.00619,
                    0.85453
                ],
                [
                    -0.58304,
                    1.20859,
                    1.97083
                ]
            ],
            [
                [
                    2.18192,
                    -0.57444,
                    -0.53008
                ],
                [
                    -0.61141,
                    2.0063,
                    -0.85461
                ],
                [
                    -0.58304,
                    -1.20859,
                    1.97083
                ]
            ],
            [
                [
                    2.18193,
                    0.57443,
                    -0.53009
                ],
                [
                    0.61141,
                    2.0063,
                    0.85461
                ],
                [
                    -0.58298,
                    1.20857,
                    1.97083
                ]
            ],
            [
                [
                    -1.88469,
                    -0.44837,
                    -0.36946
                ],
                [
                    -0.45481,
                    -1.4687,
                    -0.18575
                ],
                [
                    -0.36808,
                    -0.13561,
                    -1.98666
                ]
            ],
            [
                [
                    -1.88469,
                    0.44837,
                    -0.36944
                ],
                [
                    0.45481,
                    -1.4687,
                    0.18575
                ],
                [
                    -0.36806,
                    0.13556,
                    -1.98667
                ]
            ],
            [
                [
                    -1.88469,
                    -0.44837,
                    -0.36944
                ],
                [
                    -0.45476,
                    -1.46874,
                    -0.1856
                ],
                [
                    -0.36806,
                    -0.13556,
                    -1.98667
                ]
            ],
            [
                [
                    -1.88469,
                    0.44837,
                    -0.36946
                ],
                [
                    0.45476,
                    -1.46874,
                    0.1856
                ],
                [
                    -0.36808,
                    0.13561,
                    -1.98666
                ]
            ],
            [
                [
                    -1.50619,
                    -0.14812,
                    0.29527
                ],
                [
                    -0.1154,
                    -1.83715,
                    0.40966
                ],
                [
                    0.38327,
                    0.55899,
                    -2.19224
                ]
            ],
            [
                [
                    -1.5062,
                    0.14813,
                    0.29531
                ],
                [
                    0.1154,
                    -1.83715,
                    -0.40966
                ],
                [
                    0.38327,
                    -0.55906,
                    -2.19222
                ]
            ],
            [
                [
                    -1.5062,
                    -0.14813,
                    0.29531
                ],
                [
                    -0.11544,
                    -1.83718,
                    0.40968
                ],
                [
                    0.38327,
                    0.55906,
                    -2.19222
                ]
            ],
            [
                [
                    -1.50619,
                    0.14812,
                    0.29527
                ],
                [
                    0.11544,
                    -1.83718,
                    -0.40968
                ],
                [
                    0.38327,
                    -0.55899,
                    -2.19224
                ]
            ],
            [
                [
                    -2.46897,
                    -0.54288,
                    0.16213
                ],
                [
                    -0.59512,
                    -1.70284,
                    0.15228
                ],
                [
                    0.05708,
                    0.13934,
                    -1.52806
                ]
            ],
            [
                [
                    -2.46901,
                    0.54289,
                    0.16212
                ],
                [
                    0.59512,
                    -1.70284,
                    -0.15228
                ],
                [
                    0.05693,
                    -0.13929,
                    -1.52808
                ]
            ],
            [
                [
                    -2.46901,
                    -0.54289,
                    0.16212
                ],
                [
                    -0.59495,
                    -1.70265,
                    0.15223
                ],
                [
                    0.05693,
                    0.13929,
                    -1.52808
                ]
            ],
            [
                [
                    -2.46897,
                    0.54288,
                    0.16213
                ],
                [
                    0.59495,
                    -1.70265,
                    -0.15223
                ],
                [
                    0.05708,
                    -0.13934,
                    -1.52806
                ]
            ],
            [
                [
                    -1.87638,
                    -0.33929,
                    -0.09346
                ],
                [
                    -0.46478,
                    -1.99593,
                    -0.23747
                ],
                [
                    -0.16572,
                    -0.42697,
                    -1.6091
                ]
            ],
            [
                [
                    -1.87635,
                    0.3393,
                    -0.09347
                ],
                [
                    0.46478,
                    -1.99593,
                    0.23747
                ],
                [
                    -0.1658,
                    0.42712,
                    -1.60907
                ]
            ],
            [
                [
                    -1.87635,
                    -0.3393,
                    -0.09347
                ],
                [
                    -0.46479,
                    -1.99572,
                    -0.23743
                ],
                [
                    -0.1658,
                    -0.42712,
                    -1.60907
                ]
            ],
            [
                [
                    -1.87638,
                    0.33929,
                    -0.09346
                ],
                [
                    0.46479,
                    -1.99572,
                    0.23743
                ],
                [
                    -0.16572,
                    0.42697,
                    -1.6091
                ]
            ],
            [
                [
                    -1.94365,
                    -0.35637,
                    0.84382
                ],
                [
                    -0.34364,
                    -1.08132,
                    0.05637
                ],
                [
                    0.78662,
                    -0.03005,
                    -2.23344
                ]
            ],
            [
                [
                    -1.94367,
                    0.35638,
                    0.84382
                ],
                [
                    0.34364,
                    -1.08132,
                    -0.05637
                ],
                [
                    0.7866,
                    0.03007,
                    -2.23347
                ]
            ],
            [
                [
                    -1.94367,
                    -0.35638,
                    0.84382
                ],
                [
                    -0.34357,
                    -1.08125,
                    0.05634
                ],
                [
                    0.7866,
                    -0.03007,
                    -2.23347
                ]
            ],
            [
                [
                    -1.94365,
                    0.35637,
                    0.84382
                ],
                [
                    0.34357,
                    -1.08125,
                    -0.05634
                ],
                [
                    0.78662,
                    0.03005,
                    -2.23344
                ]
            ]
        ]
    },
    "band_gap": 3.2979000000000003,
    "is_direct": false,
    "formula": "SrCdB2O5"
}